Workbook
Name Slicer_month: #N/A
Name Slicer_year: #N/A

Sheet an
F2: companies with maximum total laid off and maximum percentage laid off
A3: Row Labels | B3: Sum of total_laid_off | F3: companies with maximum funds raised millions
A4: 99 | B4: 75 | F4: Companies with the Highest Total Layoffs top 10
A5: #Paid | B5: 19 | F5: industries with the Highest Total Layoffs | Q5: loft | R5: 6 | BH5: Row Labels | BI5: Sum of total_laid_off | CA5: country | CB5: (All)
A6: &Open | B6: 9 | F6: countries with the Highest Total Layoffs | BH6: Amazon | BI6: 18150 | BY6: total laid off
A7: 100 Thieves | B7: 12 | BH7: Google | BI7: 12000 | BK7: Count of company | BW7: Sum of total_laid_off | CA7: Sum of total_laid_off
A8: 10X Genomics | B8: 100 | D8: Row Labels | E8: =VLOOKUP(D:D,A3:B827,2,0) -> Sum of total_laid_off | H8: company with maximum total laid off for years | L8: company with high raised million | P8: company with high total layoffs | AB8: country with high laid_off | BH8: Meta | BI8: 11000 | BK8: 1994 | BW8: 383159 | CA8: 383159
A9: 1stdibs | B9: 70 | C9: =RANK(E:E,E:E) -> #N/A | D9: 99 | E9: =VLOOKUP(D:D,A4:B828,2,0) -> 75 | H9: =VLOOKUP(1,C9:E831,2,0) -> #N/A | I9: =VLOOKUP(1,C9:E831,3,0) -> #N/A | J9: 3 | M9: =VLOOKUP(1,I13:L835, 2,0) -> Byju's | N9: =VLOOKUP(1,I13:L835,4,0) -> 35600 | P9: =VLOOKUP(1,M13:O835,2,0) -> Loft | Q9: =VLOOKUP(1,M13:O835,3,0) -> 6 | W9: industrie with high laid_off | AB9: =VLOOKUP(1,Y12:AA835,2,0) -> United States | AD9: =VLOOKUP(1,Y12:AA835,3,0) -> 256059 | BH9: Salesforce | BI9: 10090 | CB9: =GETPIVOTDATA("total_laid_off",$CA$7) -> 383159
A10: 2TM | B10: 190 | C10: =RANK(E:E,E:E) -> #N/A | D10: #Paid | E10: =VLOOKUP(D:D,A5:B829,2,0) -> 19 | W10: =VLOOKUP(1,T12:V42,2,0) -> #N/A | X10: =VLOOKUP(1,T12:V42,3,0) -> #N/A | BH10: Philips | BI10: 10000 | BW10: =GETPIVOTDATA("total_laid_off",$BW$7) -> 383159
A11: 2U | B11: 0 | C11: =RANK(E:E,E:E) -> #N/A | D11: &Open | E11: =VLOOKUP(D:D,A6:B830,2,0) -> 9 | U11: industry | V11: Sum of total_laid_off | Z11: country | AA11: Sum of total_laid_off | BH11: Microsoft | BI11: 10000
A12: 54gene | B12: 95 | C12: =RANK(E:E,E:E) -> #N/A | D12: 100 Thieves | E12: =VLOOKUP(D:D,A7:B831,2,0) -> 12 | G12: Row Labels | H12: Sum of funds_raised_millions | J12: Row Labels | L12: funds raised million | N12: Row Labels | O12: Count of total_laid_off | T12: =RANK(V:V,V:V) -> #REF! | U12: Aerospace | V12: 661 | Y12: =RANK(AA:AA,AA:AA) -> 23 | Z12: Argentina | AA12: 323 | AQ12: Row Labels | AR12: Sum of funds_raised_millions | BH12: Ericsson | BI12: 8500 | BW12: =GETPIVOTDATA("total_laid_off",$BW$7) -> 383159 | BX12: =GETPIVOTDATA("total_laid_off",$BW$7) -> 383159
A13: 5B Solar | B13: 0 | C13: =RANK(E:E,E:E) -> #N/A | D13: 10X Genomics | E13: =VLOOKUP(D:D,A8:B832,2,0) -> 100 | G13: 99 | H13: 244 | I13: =RANK(L:L,L:L) -> 281 | J13: 99 | L13: =VLOOKUP(G13,G12:H835,2,0) -> 244 | M13: =RANK(O:O,O:O) -> 286 | N13: 99 | O13: 1 | T13: =RANK(V:V,V:V) -> #REF! | U13: Construction | V13: 3863 | Y13: =RANK(AA:AA,AA:AA) -> 14 | Z13: Australia | AA13: 2324 | AI13: Sum of total_laid_off | AL13: Sum of total_laid_off | AQ13: Ola | AR13: 18800 | BH13: Uber | BI13: 7585 | CA13: sum
A14: 6sense | B14: 150 | C14: =RANK(E:E,E:E) -> #N/A | D14: 1stdibs | E14: =VLOOKUP(D:D,A9:B833,2,0) -> 70 | G14: #Paid | H14: 21 | I14: =RANK(L:L,L:L) -> 636 | J14: #Paid | L14: =VLOOKUP(G14,G13:H836,2,0) -> 21 | M14: =RANK(O:O,O:O) -> 286 | N14: #Paid | O14: 1 | T14: =RANK(V:V,V:V) -> #REF! | U14: Consumer | V14: 45182 | Y14: =RANK(AA:AA,AA:AA) -> 19 | Z14: Austria | AA14: 570 | AE14: Sum of total_laid_off | AI14: 383159 | AL14: 383159 | AQ14: Tesla | AR14: 20200 | BH14: Dell | BI14: 6650 | BZ14: Amazon | CA14: 18150
A15: 80 Acres Farms | B15: 0 | C15: =RANK(E:E,E:E) -> #N/A | D15: 2TM | E15: =VLOOKUP(D:D,A10:B834,2,0) -> 190 | G15: &Open | H15: 35 | I15: =RANK(L:L,L:L) -> 587 | J15: &Open | L15: =VLOOKUP(G15,G14:H837,2,0) -> 35 | M15: =RANK(O:O,O:O) -> 286 | N15: &Open | O15: 1 | T15: =RANK(V:V,V:V) -> #REF! | U15: crypto | V15: 10693 | Y15: =RANK(AA:AA,AA:AA) -> 6 | Z15: Brazil | AA15: 10391 | AE15: 383159 | AQ15: Rivian | AR15: 24500 | BH15: Booking.com | BI15: 4601
A16: 8x8 | B16: 355 | C16: =RANK(E:E,E:E) -> #N/A | D16: 2U | E16: =VLOOKUP(D:D,A11:B835,2,0) -> 0 | G16: 100 Thieves | H16: 120 | I16: =RANK(L:L,L:L) -> 406 | J16: 100 Thieves | L16: =VLOOKUP(G16,G15:H838,2,0) -> 120 | M16: =RANK(O:O,O:O) -> 286 | N16: 100 Thieves | O16: 1 | T16: =RANK(V:V,V:V) -> #REF! | U16: Data | V16: 5135 | Y16: =RANK(AA:AA,AA:AA) -> 9 | Z16: Canada | AA16: 6319 | AQ16: Meta | AR16: 26000
A17: 98point6 | B17: 0 | C17: =RANK(E:E,E:E) -> #N/A | D17: 54gene | E17: =VLOOKUP(D:D,A12:B836,2,0) -> 95 | G17: 10X Genomics | H17: 242 | I17: =RANK(L:L,L:L) -> 286 | J17: 10X Genomics | L17: =VLOOKUP(G17,G16:H839,2,0) -> 242 | M17: =RANK(O:O,O:O) -> 286 | N17: 10X Genomics | O17: 1 | T17: =RANK(V:V,V:V) -> #REF! | U17: Education | V17: 13338 | Y17: =RANK(AA:AA,AA:AA) -> 44 | Z17: Chile | AA17: 30 | AQ17: Delivery Hero | AR17: 26500
A18: Abra | B18: 12 | C18: =RANK(E:E,E:E) -> #N/A | D18: 5B Solar | E18: =VLOOKUP(D:D,A13:B837,2,0) -> 0 | G18: 1stdibs | H18: 253 | I18: =RANK(L:L,L:L) -> 275 | J18: 1stdibs | L18: =VLOOKUP(G18,G17:H840,2,0) -> 253 | M18: =RANK(O:O,O:O) -> 286 | N18: 1stdibs | O18: 1 | T18: =RANK(V:V,V:V) -> #REF! | U18: Energy | V18: 802 | Y18: =RANK(AA:AA,AA:AA) -> 11 | Z18: China | AA18: 5905 | AQ18: Bytedance | AR18: 35600
A19: Absci | B19: 40 | C19: =RANK(E:E,E:E) -> #N/A | D19: 6sense | E19: =VLOOKUP(D:D,A14:B838,2,0) -> 150 | G19: 2TM | H19: 500 | I19: =RANK(L:L,L:L) -> 164 | J19: 2TM | L19: =VLOOKUP(G19,G18:H841,2,0) -> 500 | M19: =RANK(O:O,O:O) -> 60 | N19: 2TM | O19: 2 | T19: =RANK(V:V,V:V) -> #REF! | U19: Finance | V19: 28344 | Y19: =RANK(AA:AA,AA:AA) -> 32 | Z19: Colombia | AA19: 130 | AQ19: Twitter | AR19: 38700
A20: Acast | B20: 70 | C20: =RANK(E:E,E:E) -> #N/A | D20: 80 Acres Farms | E20: =VLOOKUP(D:D,A15:B839,2,0) -> 0 | G20: 2U | H20: 426 | I20: =RANK(L:L,L:L) -> 185 | J20: 2U | L20: =VLOOKUP(G20,G19:H842,2,0) -> 426 | M20: =RANK(O:O,O:O) -> 286 | N20: 2U | O20: 1 | T20: =RANK(V:V,V:V) -> #REF! | U20: Fin-Tech | V20: 215 | Y20: =RANK(AA:AA,AA:AA) -> 29 | Z20: Denmark | AA20: 240 | AQ20: WeWork | AR20: 65700
A21: Acko | B21: 45 | C21: =RANK(E:E,E:E) -> #N/A | D21: 8x8 | E21: =VLOOKUP(D:D,A16:B840,2,0) -> 355 | G21: 54gene | H21: 44 | I21: =RANK(L:L,L:L) -> 561 | J21: 54gene | L21: =VLOOKUP(G21,G20:H843,2,0) -> 44 | M21: =RANK(O:O,O:O) -> 286 | N21: 54gene | O21: 1 | T21: =RANK(V:V,V:V) -> #REF! | U21: Fitness | V21: 8748 | Y21: =RANK(AA:AA,AA:AA) -> 27 | Z21: Finland | AA21: 250 | AQ21: Uber | AR21: 123500
A22: Acorns | B22: 50 | C22: =RANK(E:E,E:E) -> #N/A | D22: 98point6 | E22: =VLOOKUP(D:D,A17:B841,2,0) -> 0 | G22: 5B Solar | H22: 12 | I22: =RANK(L:L,L:L) -> 679 | J22: 5B Solar | L22: =VLOOKUP(G22,G21:H844,2,0) -> 12 | M22: =RANK(O:O,O:O) -> 286 | N22: 5B Solar | O22: 1 | T22: =RANK(V:V,V:V) -> #REF! | U22: Food | V22: 22855 | Y22: =RANK(AA:AA,AA:AA) -> 17 | Z22: France | AA22: 915 | AD22: category | AE22: sum of total laid off | AQ22: Netflix | AR22: 487600
A23: Actifio | B23: 54 | C23: =RANK(E:E,E:E) -> #N/A | D23: Abra | E23: =VLOOKUP(D:D,A18:B842,2,0) -> 12 | G23: 6sense | H23: 426 | I23: =RANK(L:L,L:L) -> 185 | J23: 6sense | L23: =VLOOKUP(G23,G22:H845,2,0) -> 426 | M23: =RANK(O:O,O:O) -> 286 | N23: 6sense | O23: 1 | T23: =RANK(V:V,V:V) -> #REF! | U23: Hardware | V23: 13828 | Y23: =RANK(AA:AA,AA:AA) -> 7 | Z23: Germany | AA23: 8701 | AD23: large reduction | AE23: 1399
A24: ActiveCampaign | B24: 0 | C24: =RANK(E:E,E:E) -> #N/A | D24: Absci | E24: =VLOOKUP(D:D,A19:B843,2,0) -> 40 | G24: 80 Acres Farms | H24: 275 | I24: =RANK(L:L,L:L) -> 261 | J24: 80 Acres Farms | L24: =VLOOKUP(G24,G23:H846,2,0) -> 275 | M24: =RANK(O:O,O:O) -> 286 | N24: 80 Acres Farms | O24: 1 | T24: =RANK(V:V,V:V) -> #REF! | U24: Healthcare | V24: 25953 | Y24: =RANK(AA:AA,AA:AA) -> 18 | Z24: Hong Kong | AA24: 730 | AD24: medium reduction | AE24: 69394
A25: Ada | B25: 78 | C25: =RANK(E:E,E:E) -> #N/A | D25: Acast | E25: =VLOOKUP(D:D,A20:B844,2,0) -> 70 | G25: 8x8 | H25: 506 | I25: =RANK(L:L,L:L) -> 162 | J25: 8x8 | L25: =VLOOKUP(G25,G24:H847,2,0) -> 506 | M25: =RANK(O:O,O:O) -> 60 | N25: 8x8 | O25: 2 | T25: =RANK(V:V,V:V) -> #REF! | U25: HR | V25: 2783 | Y25: =RANK(AA:AA,AA:AA) -> 1388 | Z25: Hungary | AA25: 0 | AD25: shutdown | AE25: 7401 | AR25: Row Labels | AS25: Sum of funds_raised_millions
A26: Ada Health | B26: 50 | C26: =RANK(E:E,E:E) -> #N/A | D26: Acko | E26: =VLOOKUP(D:D,A21:B845,2,0) -> 45 | G26: 98point6 | H26: 247 | I26: =RANK(L:L,L:L) -> 277 | J26: 98point6 | L26: =VLOOKUP(G26,G25:H848,2,0) -> 247 | M26: =RANK(O:O,O:O) -> 286 | N26: 98point6 | O26: 1 | T26: =RANK(V:V,V:V) -> #REF! | U26: Infrastructure | V26: 5785 | Y26: =RANK(AA:AA,AA:AA) -> 3 | Z26: India | AA26: 35993 | AD26: small reduction | AE26: 86140 | AR26: Travel | AS26: 33279
A27: Ada Support | B27: 36 | C27: =RANK(E:E,E:E) -> #N/A | D27: Acorns | E27: =VLOOKUP(D:D,A22:B846,2,0) -> 50 | G27: Abra | H27: 106 | I27: =RANK(L:L,L:L) -> 427 | J27: Abra | L27: =VLOOKUP(G27,G26:H849,2,0) -> 106 | M27: =RANK(O:O,O:O) -> 286 | N27: Abra | O27: 1 | T27: =RANK(V:V,V:V) -> #REF! | U27: Legal | V27: 836 | Y27: =RANK(AA:AA,AA:AA) -> 13 | Z27: Indonesia | AA27: 3521 | AD27: unknown | AE27: 29033 | AR27: Other | AS27: 35106
A28: Adaptive Biotechnologies | B28: 100 | C28: =RANK(E:E,E:E) -> #N/A | D28: Actifio | E28: =VLOOKUP(D:D,A23:B847,2,0) -> 54 | G28: Absci | H28: 237 | I28: =RANK(L:L,L:L) -> 290 | J28: Absci | L28: =VLOOKUP(G28,G27:H850,2,0) -> 237 | M28: =RANK(O:O,O:O) -> 286 | N28: Absci | O28: 1 | T28: =RANK(V:V,V:V) -> #REF! | U28: Logistics | V28: 4026 | Y28: =RANK(AA:AA,AA:AA) -> 26 | Z28: Ireland | AA28: 257 | AR28: Healthcare | AS28: 51166
A29: Addepar | B29: 20 | C29: =RANK(E:E,E:E) -> #N/A | D29: ActiveCampaign | E29: =VLOOKUP(D:D,A24:B848,2,0) -> 0 | G29: Acast | H29: 126 | I29: =RANK(L:L,L:L) -> 400 | J29: Acast | L29: =VLOOKUP(G29,G28:H851,2,0) -> 126 | M29: =RANK(O:O,O:O) -> 286 | N29: Acast | O29: 1 | T29: =RANK(V:V,V:V) -> #REF! | U29: Manufacturing | V29: 20 | Y29: =RANK(AA:AA,AA:AA) -> 12 | Z29: Israel | AA29: 3638 | AR29: Retail | AS29: 61688
A30: Adobe | B30: 100 | C30: =RANK(E:E,E:E) -> #N/A | D30: Ada | E30: =VLOOKUP(D:D,A25:B849,2,0) -> 78 | G30: Acko | H30: 143 | I30: =RANK(L:L,L:L) -> 381 | J30: Acko | L30: =VLOOKUP(G30,G29:H852,2,0) -> 143 | M30: =RANK(O:O,O:O) -> 286 | N30: Acko | O30: 1 | T30: =RANK(V:V,V:V) -> #REF! | U30: Marketing | V30: 10258 | Y30: =RANK(AA:AA,AA:AA) -> 1388 | Z30: Italy | AA30: 0 | AR30: Finance | AS30: 95658
A31: AdRoll | B31: 210 | C31: =RANK(E:E,E:E) -> #N/A | D31: Ada Health | E31: =VLOOKUP(D:D,A26:B850,2,0) -> 50 | G31: Acorns | H31: 207 | I31: =RANK(L:L,L:L) -> 313 | J31: Acorns | L31: =VLOOKUP(G31,G30:H853,2,0) -> 207 | M31: =RANK(O:O,O:O) -> 286 | N31: Acorns | O31: 1 | T31: =RANK(V:V,V:V) -> #REF! | U31: Media | V31: 5234 | Y31: =RANK(AA:AA,AA:AA) -> 36 | Z31: Japan | AA31: 85 | AR31: Food | AS31: 96747
A32: Advata | B32: 32 | C32: =RANK(E:E,E:E) -> #N/A | D32: Ada Support | E32: =VLOOKUP(D:D,A27:B851,2,0) -> 36 | G32: Actifio | H32: 352 | I32: =RANK(L:L,L:L) -> 215 | J32: Actifio | L32: =VLOOKUP(G32,G31:H854,2,0) -> 352 | M32: =RANK(O:O,O:O) -> 286 | N32: Actifio | O32: 1 | T32: =RANK(V:V,V:V) -> #REF! | U32: NULL | V32: 0 | Y32: =RANK(AA:AA,AA:AA) -> 21 | Z32: Kenya | AA32: 349 | AR32: Real Estate | AS32: 97598
A33: Adwerx | B33: 40 | C33: =RANK(E:E,E:E) -> #N/A | D33: Adaptive Biotechnologies | E33: =VLOOKUP(D:D,A28:B852,2,0) -> 100 | G33: ActiveCampaign | H33: 360 | I33: =RANK(L:L,L:L) -> 211 | J33: ActiveCampaign | L33: =VLOOKUP(G33,G32:H855,2,0) -> 360 | M33: =RANK(O:O,O:O) -> 286 | N33: ActiveCampaign | O33: 1 | T33: =RANK(V:V,V:V) -> #REF! | U33: Other | V33: 35789 | Y33: =RANK(AA:AA,AA:AA) -> 35 | Z33: Malaysia | AA33: 100 | AR33: Consumer | AS33: 154189
A34: Affirm | B34: 500 | C34: =RANK(E:E,E:E) -> #N/A | D34: Addepar | E34: =VLOOKUP(D:D,A29:B853,2,0) -> 20 | G34: Ada | H34: 190 | I34: =RANK(L:L,L:L) -> 329 | J34: Ada | L34: =VLOOKUP(G34,G33:H856,2,0) -> 190 | M34: =RANK(O:O,O:O) -> 286 | N34: Ada | O34: 1 | T34: =RANK(V:V,V:V) -> #REF! | U34: Product | V34: 1233 | Y34: =RANK(AA:AA,AA:AA) -> 25 | Z34: Mexico | AA34: 270 | AR34: Transportation | AS34: 286810
A35: Afterverse | B35: 60 | C35: =RANK(E:E,E:E) -> #N/A | D35: Adobe | E35: =VLOOKUP(D:D,A30:B854,2,0) -> 100 | G35: Ada Health | H35: 189 | I35: =RANK(L:L,L:L) -> 333 | J35: Ada Health | L35: =VLOOKUP(G35,G34:H857,2,0) -> 189 | M35: =RANK(O:O,O:O) -> 286 | N35: Ada Health | O35: 1 | T35: =RANK(V:V,V:V) -> #REF! | U35: Real Estate | V35: 17565 | Y35: =RANK(AA:AA,AA:AA) -> 30 | Z35: Myanmar | AA35: 200 | AR35: Media | AS35: 504784
A36: Agoda | B36: 1500 | C36: =RANK(E:E,E:E) -> #N/A | D36: AdRoll | E36: =VLOOKUP(D:D,A31:B855,2,0) -> 210 | G36: Ada Support | H36: 60 | I36: =RANK(L:L,L:L) -> 512 | J36: Ada Support | L36: =VLOOKUP(G36,G35:H858,2,0) -> 60 | M36: =RANK(O:O,O:O) -> 286 | N36: Ada Support | O36: 1 | T36: =RANK(V:V,V:V) -> #REF! | U36: Recruiting | V36: 2775 | Y36: =RANK(AA:AA,AA:AA) -> 4 | Z36: Netherlands | AA36: 17220
A37: Ahead | B37: 44 | C37: =RANK(E:E,E:E) -> #N/A | D37: Advata | E37: =VLOOKUP(D:D,A32:B856,2,0) -> 32 | G37: Adaptive Biotechnologies | H37: 406 | I37: =RANK(L:L,L:L) -> 194 | J37: Adaptive Biotechnologies | L37: =VLOOKUP(G37,G36:H859,2,0) -> 406 | M37: =RANK(O:O,O:O) -> 286 | N37: Adaptive Biotechnologies | O37: 1 | T37: =RANK(V:V,V:V) -> #REF! | U37: Retail | V37: 43613 | Y37: =RANK(AA:AA,AA:AA) -> 42 | Z37: New Zealand | AA37: 45
A38: Air | B38: 0 | C38: =RANK(E:E,E:E) -> #N/A | D38: Adwerx | E38: =VLOOKUP(D:D,A33:B857,2,0) -> 40 | G38: Addepar | H38: 491 | I38: =RANK(L:L,L:L) -> 166 | J38: Addepar | L38: =VLOOKUP(G38,G37:H860,2,0) -> 491 | M38: =RANK(O:O,O:O) -> 286 | N38: Addepar | O38: 1 | T38: =RANK(V:V,V:V) -> #REF! | U38: Sales | V38: 13216 | Y38: =RANK(AA:AA,AA:AA) -> 15 | Z38: Nigeria | AA38: 1882
A39: Airbnb | B39: 1930 | C39: =RANK(E:E,E:E) -> #N/A | D39: Affirm | E39: =VLOOKUP(D:D,A34:B858,2,0) -> 500 | G39: Adobe | H39: 2 | I39: =RANK(L:L,L:L) -> 725 | J39: Adobe | L39: =VLOOKUP(G39,G38:H861,2,0) -> 2 | M39: =RANK(O:O,O:O) -> 286 | N39: Adobe | O39: 1 | T39: =RANK(V:V,V:V) -> #REF! | U39: Security | V39: 5979 | Y39: =RANK(AA:AA,AA:AA) -> 1388 | Z39: Pakistan | AA39: 0
A40: Airlift | B40: 0 | C40: =RANK(E:E,E:E) -> #N/A | D40: Afterverse | E40: =VLOOKUP(D:D,A35:B859,2,0) -> 60 | G40: AdRoll | H40: 89 | I40: =RANK(L:L,L:L) -> 457 | J40: AdRoll | L40: =VLOOKUP(G40,G39:H862,2,0) -> 89 | M40: =RANK(O:O,O:O) -> 286 | N40: AdRoll | O40: 1 | T40: =RANK(V:V,V:V) -> #REF! | U40: Support | V40: 3523 | Y40: =RANK(AA:AA,AA:AA) -> 45 | Z40: Poland | AA40: 25
A41: Airtable | B41: 254 | C41: =RANK(E:E,E:E) -> #N/A | D41: Agoda | E41: =VLOOKUP(D:D,A36:B860,2,0) -> 1500 | G41: Advata | H41: 0 | I41: =RANK(L:L,L:L) -> 742 | J41: Advata | L41: =VLOOKUP(G41,G40:H863,2,0) -> 0 | M41: =RANK(O:O,O:O) -> 286 | N41: Advata | O41: 1 | T41: =RANK(V:V,V:V) -> #REF! | U41: Transportation | V41: 33748 | Y41: =RANK(AA:AA,AA:AA) -> 37 | Z41: Romania | AA41: 80
A42: Airtame | B42: 15 | C42: =RANK(E:E,E:E) -> #N/A | D42: Ahead | E42: =VLOOKUP(D:D,A37:B861,2,0) -> 44 | G42: Adwerx | H42: 20 | I42: =RANK(L:L,L:L) -> 640 | J42: Adwerx | L42: =VLOOKUP(G42,G41:H864,2,0) -> 20 | M42: =RANK(O:O,O:O) -> 286 | N42: Adwerx | O42: 1 | T42: =RANK(V:V,V:V) -> #REF! | U42: Travel | V42: 17159 | Y42: =RANK(AA:AA,AA:AA) -> 20 | Z42: Russia | AA42: 400
A43: Airtime | B43: 30 | C43: =RANK(E:E,E:E) -> #N/A | D43: Air | E43: =VLOOKUP(D:D,A38:B862,2,0) -> 0 | G43: Affirm | H43: 3000 | I43: =RANK(L:L,L:L) -> 21 | J43: Affirm | L43: =VLOOKUP(G43,G42:H865,2,0) -> 3000 | M43: =RANK(O:O,O:O) -> 60 | N43: Affirm | O43: 2 | Y43: =RANK(AA:AA,AA:AA) -> 38 | Z43: Seychelles | AA43: 75
A44: Airy Rooms | B44: 0 | C44: =RANK(E:E,E:E) -> #N/A | D44: Airbnb | E44: =VLOOKUP(D:D,A39:B863,2,0) -> 1930 | G44: Afterverse | H44: 0 | I44: =RANK(L:L,L:L) -> 742 | J44: Afterverse | L44: =VLOOKUP(G44,G43:H866,2,0) -> 0 | M44: =RANK(O:O,O:O) -> 286 | N44: Afterverse | O44: 1 | Y44: =RANK(AA:AA,AA:AA) -> 10 | Z44: Singapore | AA44: 5995
A45: Aiven | B45: 0 | C45: =RANK(E:E,E:E) -> #N/A | D45: Airlift | E45: =VLOOKUP(D:D,A40:B864,2,0) -> 0 | G45: Agoda | H45: 0 | I45: =RANK(L:L,L:L) -> 742 | J45: Agoda | L45: =VLOOKUP(G45,G44:H867,2,0) -> 0 | M45: =RANK(O:O,O:O) -> 286 | N45: Agoda | O45: 1 | U45: industry | V45: Sum of total_laid_off | Y45: =RANK(AA:AA,AA:AA) -> 27 | Z45: Spain | AA45: 250
A46: Ajaib | B46: 67 | C46: =RANK(E:E,E:E) -> #N/A | D46: Airtable | E46: =VLOOKUP(D:D,A41:B865,2,0) -> 254 | G46: Ahead | H46: 9 | I46: =RANK(L:L,L:L) -> 692 | J46: Ahead | L46: =VLOOKUP(G46,G45:H868,2,0) -> 9 | M46: =RANK(O:O,O:O) -> 286 | N46: Ahead | O46: 1 | U46: Consumer | V46: 45182 | Y46: =RANK(AA:AA,AA:AA) -> 5 | Z46: Sweden | AA46: 11264
A47: Akili Labs | B47: 46 | C47: =RANK(E:E,E:E) -> #N/A | D47: Airtame | E47: =VLOOKUP(D:D,A42:B866,2,0) -> 15 | G47: Air | H47: 18 | I47: =RANK(L:L,L:L) -> 649 | J47: Air | L47: =VLOOKUP(G47,G46:H869,2,0) -> 18 | M47: =RANK(O:O,O:O) -> 286 | N47: Air | O47: 1 | U47: Retail | V47: 43613 | Y47: =RANK(AA:AA,AA:AA) -> 1388 | Z47: Turkey | AA47: 0
A48: Akulaku | B48: 100 | C48: =RANK(E:E,E:E) -> #N/A | D48: Airtime | E48: =VLOOKUP(D:D,A43:B867,2,0) -> 30 | G48: Airbnb | H48: 11800 | I48: =RANK(L:L,L:L) -> 5 | J48: Airbnb | L48: =VLOOKUP(G48,G47:H870,2,0) -> 11800 | M48: =RANK(O:O,O:O) -> 60 | N48: Airbnb | O48: 2 | U48: Other | V48: 35789 | Y48: =RANK(AA:AA,AA:AA) -> 16 | Z48: United Arab Emirates | AA48: 995
A49: AlayaCare | B49: 80 | C49: =RANK(E:E,E:E) -> #N/A | D49: Airy Rooms | E49: =VLOOKUP(D:D,A44:B868,2,0) -> 0 | G49: Airlift | H49: 218 | I49: =RANK(L:L,L:L) -> 306 | J49: Airlift | L49: =VLOOKUP(G49,G48:H871,2,0) -> 218 | M49: =RANK(O:O,O:O) -> 60 | N49: Airlift | O49: 2 | U49: Transportation | V49: 33748 | Y49: =RANK(AA:AA,AA:AA) -> 8 | Z49: United Kingdom | AA49: 6398
A50: Albert | B50: 20 | C50: =RANK(E:E,E:E) -> #N/A | D50: Aiven | E50: =VLOOKUP(D:D,A45:B869,2,0) -> 0 | G50: Airtable | H50: 1400 | I50: =RANK(L:L,L:L) -> 61 | J50: Airtable | L50: =VLOOKUP(G50,G49:H872,2,0) -> 1400 | M50: =RANK(O:O,O:O) -> 286 | N50: Airtable | O50: 1 | U50: Finance | V50: 28344 | Y50: =RANK(AA:AA,AA:AA) -> 1 | Z50: United States | AA50: 256059
A51: Alerzo | B51: 400 | C51: =RANK(E:E,E:E) -> #N/A | D51: Ajaib | E51: =VLOOKUP(D:D,A46:B870,2,0) -> 67 | G51: Airtame | H51: 7 | I51: =RANK(L:L,L:L) -> 701 | J51: Airtame | L51: =VLOOKUP(G51,G50:H873,2,0) -> 7 | M51: =RANK(O:O,O:O) -> 286 | N51: Airtame | O51: 1 | U51: Healthcare | V51: 25953 | Y51: =RANK(AA:AA,AA:AA) -> 34 | Z51: Portugal | AA51: 115
A52: Alice | B52: 176 | C52: =RANK(E:E,E:E) -> #N/A | D52: Akili Labs | E52: =VLOOKUP(D:D,A47:B871,2,0) -> 46 | G52: Airtime | H52: 33 | I52: =RANK(L:L,L:L) -> 592 | J52: Airtime | L52: =VLOOKUP(G52,G51:H874,2,0) -> 33 | M52: =RANK(O:O,O:O) -> 286 | N52: Airtime | O52: 1 | U52: Food | V52: 22855 | Y52: =RANK(AA:AA,AA:AA) -> 1388 | Z52: South Korea | AA52: 0
A53: AliExpress Russia | B53: 400 | C53: =RANK(E:E,E:E) -> #N/A | D53: Akulaku | E53: =VLOOKUP(D:D,A48:B872,2,0) -> 100 | G53: Airy Rooms | H53: 0 | I53: =RANK(L:L,L:L) -> 742 | J53: Airy Rooms | L53: =VLOOKUP(G53,G52:H875,2,0) -> 0 | M53: =RANK(O:O,O:O) -> 60 | N53: Airy Rooms | O53: 2 | U53: Real Estate | V53: 17565 | Y53: =RANK(AA:AA,AA:AA) -> 39 | Z53: Switzerland | AA53: 62 | AC53: country | AD53: Sum of total_laid_off
A54: Allbirds | B54: 23 | C54: =RANK(E:E,E:E) -> #N/A | D54: AlayaCare | E54: =VLOOKUP(D:D,A49:B873,2,0) -> 80 | G54: Aiven | H54: 420 | I54: =RANK(L:L,L:L) -> 188 | J54: Aiven | L54: =VLOOKUP(G54,G53:H876,2,0) -> 420 | M54: =RANK(O:O,O:O) -> 286 | N54: Aiven | O54: 1 | U54: Travel | V54: 17159 | Y54: =RANK(AA:AA,AA:AA) -> 31 | Z54: Norway | AA54: 140 | AC54: Brazil | AD54: 10391
A55: Alto Pharmacy | B55: 47 | C55: =RANK(E:E,E:E) -> #N/A | D55: Albert | E55: =VLOOKUP(D:D,A50:B874,2,0) -> 20 | G55: Ajaib | H55: 245 | I55: =RANK(L:L,L:L) -> 280 | J55: Ajaib | L55: =VLOOKUP(G55,G54:H877,2,0) -> 245 | M55: =RANK(O:O,O:O) -> 286 | N55: Ajaib | O55: 1 | U55: Hardware | V55: 13828 | Y55: =RANK(AA:AA,AA:AA) -> 22 | Z55: Estonia | AA55: 333 | AC55: Germany | AD55: 8701
A56: Amazon | B56: 18150 | C56: =RANK(E:E,E:E) -> #N/A | D56: Alerzo | E56: =VLOOKUP(D:D,A51:B875,2,0) -> 400 | G56: Akili Labs | H56: 0 | I56: =RANK(L:L,L:L) -> 742 | J56: Akili Labs | L56: =VLOOKUP(G56,G55:H878,2,0) -> 0 | M56: =RANK(O:O,O:O) -> 286 | N56: Akili Labs | O56: 1 | Y56: =RANK(AA:AA,AA:AA) -> 41 | Z56: Thailand | AA56: 55 | AC56: India | AD56: 35993
A57: Amber Group | B57: 0 | C57: =RANK(E:E,E:E) -> #N/A | D57: Alice | E57: =VLOOKUP(D:D,A52:B876,2,0) -> 176 | G57: Akulaku | H57: 160 | I57: =RANK(L:L,L:L) -> 362 | J57: Akulaku | L57: =VLOOKUP(G57,G56:H879,2,0) -> 160 | M57: =RANK(O:O,O:O) -> 286 | N57: Akulaku | O57: 1 | Y57: =RANK(AA:AA,AA:AA) -> 1388 | Z57: Vietnam | AA57: 0 | AC57: Netherlands | AD57: 17220
A58: Ambev Tech | B58: 50 | C58: =RANK(E:E,E:E) -> #N/A | D58: AliExpress Russia | E58: =VLOOKUP(D:D,A53:B877,2,0) -> 400 | G58: AlayaCare | H58: 293 | I58: =RANK(L:L,L:L) -> 250 | J58: AlayaCare | L58: =VLOOKUP(G58,G57:H880,2,0) -> 293 | M58: =RANK(O:O,O:O) -> 286 | N58: AlayaCare | O58: 1 | Y58: =RANK(AA:AA,AA:AA) -> 33 | Z58: Bulgaria | AA58: 120 | AC58: Sweden | AD58: 11264
A59: Amdocs | B59: 700 | C59: =RANK(E:E,E:E) -> #N/A | D59: Allbirds | E59: =VLOOKUP(D:D,A54:B878,2,0) -> 23 | G59: Albert | H59: 175 | I59: =RANK(L:L,L:L) -> 347 | J59: Albert | L59: =VLOOKUP(G59,G58:H881,2,0) -> 175 | M59: =RANK(O:O,O:O) -> 286 | N59: Albert | O59: 1 | Y59: =RANK(AA:AA,AA:AA) -> 1388 | Z59: Egypt | AA59: 0 | AC59: United States | AD59: 256059 | AK59: country | AL59: Sum of total_laid_off
A60: American Robotics | B60: 50 | C60: =RANK(E:E,E:E) -> #N/A | D60: Alto Pharmacy | E60: =VLOOKUP(D:D,A55:B879,2,0) -> 47 | G60: Alerzo | H60: 16 | I60: =RANK(L:L,L:L) -> 659 | J60: Alerzo | L60: =VLOOKUP(G60,G59:H882,2,0) -> 16 | M60: =RANK(O:O,O:O) -> 286 | N60: Alerzo | O60: 1 | Y60: =RANK(AA:AA,AA:AA) -> 42 | Z60: Luxembourg | AA60: 45 | AK60: Brazil | AL60: 10391
A61: Amount | B61: 130 | C61: =RANK(E:E,E:E) -> #N/A | D61: Amazon | E61: =VLOOKUP(D:D,A56:B880,2,0) -> 18150 | G61: Alice | H61: 348 | I61: =RANK(L:L,L:L) -> 221 | J61: Alice | L61: =VLOOKUP(G61,G60:H883,2,0) -> 348 | M61: =RANK(O:O,O:O) -> 60 | N61: Alice | O61: 2 | Y61: =RANK(AA:AA,AA:AA) -> 40 | Z61: Lithuania | AA61: 60 | AK61: Germany | AL61: 8701
A62: Amperity | B62: 13 | C62: =RANK(E:E,E:E) -> #N/A | D62: Amber Group | E62: =VLOOKUP(D:D,A57:B881,2,0) -> 0 | G62: AliExpress Russia | H62: 60 | I62: =RANK(L:L,L:L) -> 512 | J62: AliExpress Russia | L62: =VLOOKUP(G62,G61:H884,2,0) -> 60 | M62: =RANK(O:O,O:O) -> 286 | N62: AliExpress Russia | O62: 1 | Y62: =RANK(AA:AA,AA:AA) -> 24 | Z62: Senegal | AA62: 300 | AK62: India | AL62: 35993
A63: Amplero | B63: 17 | C63: =RANK(E:E,E:E) -> #N/A | D63: Ambev Tech | E63: =VLOOKUP(D:D,A58:B882,2,0) -> 50 | G63: Allbirds | H63: 202 | I63: =RANK(L:L,L:L) -> 317 | J63: Allbirds | L63: =VLOOKUP(G63,G62:H885,2,0) -> 202 | M63: =RANK(O:O,O:O) -> 286 | N63: Allbirds | O63: 1 | Y63: =RANK(AA:AA,AA:AA) -> 1388 | AK63: Netherlands | AL63: 17220
A64: Anagram | B64: 17 | C64: =RANK(E:E,E:E) -> #N/A | D64: Amdocs | E64: =VLOOKUP(D:D,A59:B883,2,0) -> 700 | G64: Alto Pharmacy | H64: 356 | I64: =RANK(L:L,L:L) -> 213 | J64: Alto Pharmacy | L64: =VLOOKUP(G64,G63:H886,2,0) -> 356 | M64: =RANK(O:O,O:O) -> 286 | N64: Alto Pharmacy | O64: 1 | Y64: =RANK(AA:AA,AA:AA) -> 1388 | AC64: india | AD64: 13929 | AK64: Sweden | AL64: 11264
A65: Andela | B65: 135 | C65: =RANK(E:E,E:E) -> #N/A | D65: American Robotics | E65: =VLOOKUP(D:D,A60:B884,2,0) -> 50 | G65: Amazon | H65: 324 | I65: =RANK(L:L,L:L) -> 233 | J65: Amazon | L65: =VLOOKUP(G65,G64:H887,2,0) -> 324 | M65: =RANK(O:O,O:O) -> 19 | N65: Amazon | O65: 3 | Y65: =RANK(AA:AA,AA:AA) -> 1388 | AC65: netherlands | AD65: 4765 | AK65: United States | AL65: 256059
A66: AngelList | B66: 20 | C66: =RANK(E:E,E:E) -> #N/A | D66: Amount | E66: =VLOOKUP(D:D,A61:B885,2,0) -> 130 | G66: Amber Group | H66: 328 | I66: =RANK(L:L,L:L) -> 230 | J66: Amber Group | L66: =VLOOKUP(G66,G65:H888,2,0) -> 328 | M66: =RANK(O:O,O:O) -> 286 | N66: Amber Group | O66: 1 | Y66: =RANK(AA:AA,AA:AA) -> 1388 | AC66: singapore | AD66: 5550
A67: Anodot | B67: 35 | C67: =RANK(E:E,E:E) -> #N/A | D67: Amperity | E67: =VLOOKUP(D:D,A62:B886,2,0) -> 13 | G67: Ambev Tech | H67: 0 | I67: =RANK(L:L,L:L) -> 742 | J67: Ambev Tech | L67: =VLOOKUP(G67,G66:H889,2,0) -> 0 | M67: =RANK(O:O,O:O) -> 286 | N67: Ambev Tech | O67: 1 | Y67: =RANK(AA:AA,AA:AA) -> 1388 | AC67: sweden | AD67: 10124
A68: Antidote Health | B68: 23 | C68: =RANK(E:E,E:E) -> #N/A | D68: Amplero | E68: =VLOOKUP(D:D,A63:B887,2,0) -> 17 | G68: Amdocs | H68: 0 | I68: =RANK(L:L,L:L) -> 742 | J68: Amdocs | L68: =VLOOKUP(G68,G67:H890,2,0) -> 0 | M68: =RANK(O:O,O:O) -> 286 | N68: Amdocs | O68: 1 | Y68: =RANK(AA:AA,AA:AA) -> 1388 | AC68: united states | AD68: 130761
A69: Anywell | B69: 11 | C69: =RANK(E:E,E:E) -> #N/A | D69: Anagram | E69: =VLOOKUP(D:D,A64:B888,2,0) -> 17 | G69: American Robotics | H69: 92 | I69: =RANK(L:L,L:L) -> 452 | J69: American Robotics | L69: =VLOOKUP(G69,G68:H891,2,0) -> 92 | M69: =RANK(O:O,O:O) -> 286 | N69: American Robotics | O69: 1 | Y69: =RANK(AA:AA,AA:AA) -> 1388
A70: Apartment List | B70: 29 | C70: =RANK(E:E,E:E) -> #N/A | D70: Andela | E70: =VLOOKUP(D:D,A65:B889,2,0) -> 135 | G70: Amount | H70: 566 | I70: =RANK(L:L,L:L) -> 146 | J70: Amount | L70: =VLOOKUP(G70,G69:H892,2,0) -> 566 | M70: =RANK(O:O,O:O) -> 60 | N70: Amount | O70: 2 | Y70: =RANK(AA:AA,AA:AA) -> 1388
A71: Apollo | B71: 0 | C71: =RANK(E:E,E:E) -> #N/A | D71: AngelList | E71: =VLOOKUP(D:D,A66:B890,2,0) -> 20 | G71: Amperity | H71: 187 | I71: =RANK(L:L,L:L) -> 336 | J71: Amperity | L71: =VLOOKUP(G71,G70:H893,2,0) -> 187 | M71: =RANK(O:O,O:O) -> 286 | N71: Amperity | O71: 1 | Y71: =RANK(AA:AA,AA:AA) -> 1388
A72: Apollo Insurance | B72: 0 | C72: =RANK(E:E,E:E) -> #N/A | D72: Anodot | E72: =VLOOKUP(D:D,A67:B891,2,0) -> 35 | G72: Amplero | H72: 25 | I72: =RANK(L:L,L:L) -> 618 | J72: Amplero | L72: =VLOOKUP(G72,G71:H894,2,0) -> 25 | M72: =RANK(O:O,O:O) -> 286 | N72: Amplero | O72: 1 | Y72: =RANK(AA:AA,AA:AA) -> 1388
A73: App Annie | B73: 80 | C73: =RANK(E:E,E:E) -> #N/A | D73: Antidote Health | E73: =VLOOKUP(D:D,A68:B892,2,0) -> 23 | G73: Anagram | H73: 14 | I73: =RANK(L:L,L:L) -> 671 | J73: Anagram | L73: =VLOOKUP(G73,G72:H895,2,0) -> 14 | M73: =RANK(O:O,O:O) -> 286 | N73: Anagram | O73: 1 | Y73: =RANK(AA:AA,AA:AA) -> 1388
A74: Appgate | B74: 164 | C74: =RANK(E:E,E:E) -> #N/A | D74: Anywell | E74: =VLOOKUP(D:D,A69:B893,2,0) -> 11 | G74: Andela | H74: 181 | I74: =RANK(L:L,L:L) -> 341 | J74: Andela | L74: =VLOOKUP(G74,G73:H896,2,0) -> 181 | M74: =RANK(O:O,O:O) -> 286 | N74: Andela | O74: 1 | Y74: =RANK(AA:AA,AA:AA) -> 1388
A75: AppLovin | B75: 300 | C75: =RANK(E:E,E:E) -> #N/A | D75: Apartment List | E75: =VLOOKUP(D:D,A70:B894,2,0) -> 29 | G75: AngelList | H75: 26 | I75: =RANK(L:L,L:L) -> 611 | J75: AngelList | L75: =VLOOKUP(G75,G74:H897,2,0) -> 26 | M75: =RANK(O:O,O:O) -> 286 | N75: AngelList | O75: 1 | Y75: =RANK(AA:AA,AA:AA) -> 1388
A76: ApplyBoard | B76: 90 | C76: =RANK(E:E,E:E) -> #N/A | D76: Apollo | E76: =VLOOKUP(D:D,A71:B895,2,0) -> 0 | G76: Anodot | H76: 64 | I76: =RANK(L:L,L:L) -> 503 | J76: Anodot | L76: =VLOOKUP(G76,G75:H898,2,0) -> 64 | M76: =RANK(O:O,O:O) -> 286 | N76: Anodot | O76: 1 | Y76: =RANK(AA:AA,AA:AA) -> 1388
A77: Aqgromalin | B77: 80 | C77: =RANK(E:E,E:E) -> #N/A | D77: Apollo Insurance | E77: =VLOOKUP(D:D,A72:B896,2,0) -> 0 | G77: Antidote Health | H77: 36 | I77: =RANK(L:L,L:L) -> 585 | J77: Antidote Health | L77: =VLOOKUP(G77,G76:H899,2,0) -> 36 | M77: =RANK(O:O,O:O) -> 286 | N77: Antidote Health | O77: 1 | Y77: =RANK(AA:AA,AA:AA) -> 1388
A78: Aqua Security | B78: 89 | C78: =RANK(E:E,E:E) -> #N/A | D78: App Annie | E78: =VLOOKUP(D:D,A73:B897,2,0) -> 80 | G78: Anywell | H78: 15 | I78: =RANK(L:L,L:L) -> 667 | J78: Anywell | L78: =VLOOKUP(G78,G77:H900,2,0) -> 15 | M78: =RANK(O:O,O:O) -> 286 | N78: Anywell | O78: 1 | Y78: =RANK(AA:AA,AA:AA) -> 1388
A79: Arc | B79: 13 | C79: =RANK(E:E,E:E) -> #N/A | D79: Appgate | E79: =VLOOKUP(D:D,A74:B898,2,0) -> 164 | G79: Apartment List | H79: 169 | I79: =RANK(L:L,L:L) -> 351 | J79: Apartment List | L79: =VLOOKUP(G79,G78:H901,2,0) -> 169 | M79: =RANK(O:O,O:O) -> 286 | N79: Apartment List | O79: 1 | Y79: =RANK(AA:AA,AA:AA) -> 1388
A80: Arch Oncology | B80: 0 | C80: =RANK(E:E,E:E) -> #N/A | D80: AppLovin | E80: =VLOOKUP(D:D,A75:B899,2,0) -> 300 | G80: Apollo | H80: 183 | I80: =RANK(L:L,L:L) -> 338 | J80: Apollo | L80: =VLOOKUP(G80,G79:H902,2,0) -> 183 | M80: =RANK(O:O,O:O) -> 286 | N80: Apollo | O80: 1 | Y80: =RANK(AA:AA,AA:AA) -> 1388
... A831: Lucira Health | B831: 26 | C831: =RANK(E:E,E:E) -> #N/A | D831: Loom | E831: =VLOOKUP(D:D,A826:B1650,2,0) -> #N/A | G831: Loja Integrada | H831: 0 | I831: =RANK(L:L,L:L) -> 742 | J831: Loggi | L831: =VLOOKUP(G831,G830:H1653,2,0) -> 0 | M831: =RANK(O:O,O:O) -> 286 | N831: Loja Integrada | O831: 1 | Y831: =RANK(AA:AA,AA:AA) -> 1388
A832: Lumina Networks | B832: 0 | G832: Lokalise | H832: 56 | I832: =RANK(L:L,L:L) -> 529 | J832: Loja Integrada | L832: =VLOOKUP(G832,G831:H1654,2,0) -> 56 | M832: =RANK(O:O,O:O) -> 286 | N832: Lokalise | O832: 1 | Y832: =RANK(AA:AA,AA:AA) -> 1388
A833: Lummo | B833: 150 | G833: Lola | H833: 81 | I833: =RANK(L:L,L:L) -> 471 | J833: Lokalise | L833: =VLOOKUP(G833,G832:H1655,2,0) -> 81 | M833: =RANK(O:O,O:O) -> 286 | N833: Lola | O833: 1 | Y833: =RANK(AA:AA,AA:AA) -> 1388
A834: Lunchbox | B834: 60 | G834: Loom | H834: 406 | I834: =RANK(L:L,L:L) -> 194 | J834: Lola | L834: =VLOOKUP(G834,G833:H1656,2,0) -> 406 | M834: =RANK(O:O,O:O) -> 60 | N834: Loom | O834: 2 | Y834: =RANK(AA:AA,AA:AA) -> 1388 | AL834: Sum of total_laid_off
A835: Luno | B835: 330 | G835: Loop | H835: 24 | L835: =VLOOKUP(G835,G834:H1657,2,0) -> 24 | M835: =RANK(O:O,O:O) -> 286 | N835: Loop | O835: 1 | Y835: =RANK(AA:AA,AA:AA) -> 1388 | AL835: 383159
A836: Lusha | B836: 30 | G836: Loopio | H836: 11 | N836: Loopio | O836: 1
A837: Luxury Presence | B837: 44 | G837: LoopMe | H837: 32 | K837: =GETPIVOTDATA("funds_raised_millions",$BK$7) -> #REF! | N837: LoopMe | O837: 1 | AO837: =GETPIVOTDATA("total_laid_off",$AL$834)/AO842 -> 465.56379
A838: Lyft | B838: 1742 | G838: Lora DiCarlo | H838: 9 | K838: total funds raised million | N838: Lora DiCarlo | O838: 1
A839: Lyric | B839: 100 | G839: Lucid Diagnostics | H839: 0 | N839: Lucid Diagnostics | O839: 1 | BJ839: Row Labels | BK839: Sum of funds_raised_millions | BL839: Sum of total_laid_off | BN839: Row Labels | BO839: Column1 | BP839: Column2 | BQ839: Column3
A840: Lyst | B840: 50 | G840: Lucira Health | H840: 132 | N840: Lucira Health | O840: 1 | V840: Column Labels | AA840: Column Labels | AI840: =COUNTA(AJ844:AJ1666) -> 823 | BG840: =AZ842/BF841 -> 0.92037787 | BJ840: Amazon | BK840: 324 | BL840: 18150 | BN840: 99 | BO840: =RANK(BK840:BK2466,BK840:BK2466,0) -> 19 | BP840: =RANK(BL840:BL2466,BL840:BL2466,0) -> 1 | BQ840: =Table2[[#This Row],[Column1]]+Table2[[#This Row],[Column2]] -> 20 | BW840: Metigy | BX840: 18 | BY840: 75
A841: M1 | B841: 38 | G841: Lumina Networks | H841: 10 | I841: =GETPIVOTDATA("company",$BK$7) -> 1994 | N841: Lumina Networks | O841: 1 | V841: United States | W841: Grand Total | AA841: Consumer | AB841: Grand Total | AD841: =GETPIVOTDATA("total_laid_off",$Z$840) -> 45182 | BF841: =COUNTA(BC843:BC1583) -> 741 | BJ841: Google | BK841: 26 | BL841: 12000 | BN841: #Paid | BO841: =RANK(BK841:BK2467,BK841:BK2467,0) -> 22 | BP841: =RANK(BL841:BL2467,BL841:BL2467,0) -> 1 | BQ841: =Table2[[#This Row],[Column1]]+Table2[[#This Row],[Column2]] -> 23 | BW841: Metromile | BX841: 803 | BY841: 160
A842: Made.com | B842: 0 | G842: Lummo | H842: 149 | N842: Lummo | O842: 1 | U842: Sum of total_laid_off | V842: 256059 | W842: 256059 | Z842: Sum of total_laid_off | AA842: 45182 | AB842: 45182 | AF842: Sum of funds_raised_millions | AL842: Row Labels | AM842: Count of total_laid_off | AO842: =COUNTA(AM843:AM1665) -> 823 | AW842: Row Labels | AX842: Sum of total_laid_off | AZ842: =COUNTA(AW843:AW1524) -> 682 | BC842: Row Labels | BD842: Sum of funds_raised_millions | BJ842: Meta | BK842: 26000 | BL842: 11000 | BN842: &Open | BO842: =RANK(BK842:BK2468,BK842:BK2468,0) -> 4 | BP842: =RANK(BL842:BL2468,BL842:BL2468,0) -> 1 | BQ842: =Table2[[#This Row],[Column1]]+Table2[[#This Row],[Column2]] -> 5 | BW842: MFine | BX842: 97 | BY842: 600
A843: Madefire | B843: 0 | G843: Lunchbox | H843: 72 | N843: Lunchbox | O843: 1 | AF843: 1601450 | AI843: Row Labels | AJ843: Count of funds_raised_millions | AL843: 99 | AM843: 1 | AW843: 99 | AX843: 75 | BC843: 99 | BD843: 244 | BJ843: Salesforce | BK843: 260 | BL843: 10090 | BN843: 100 Thieves | BO843: =RANK(BK843:BK2469,BK843:BK2469,0) -> 19 | BP843: =RANK(BL843:BL2469,BL843:BL2469,0) -> 1 | BQ843: =Table2[[#This Row],[Column1]]+Table2[[#This Row],[Column2]] -> 20 | BW843: Microsoft | BX843: 1 | BY843: 10000
A844: MadeiraMadeira | B844: 60 | G844: Luno | H844: 13 | N844: Luno | O844: 1 | V844: =GETPIVOTDATA("total_laid_off",$U$840,"country","United States") -> 256059 | W844: =V841 -> United States | AI844: 99 | AJ844: 1 | AL844: #Paid | AM844: 1 | AS844: =GETPIVOTDATA("total_laid_off",$AL$834)/GETPIVOTDATA("funds_raised_millions",$AF$842) -> 0.23925755 | AW844: #Paid | AX844: 19 | BC844: #Paid | BD844: 21 | BJ844: Philips | BK844: 0 | BL844: 10000 | BN844: 10X Genomics | BO844: =RANK(BK844:BK2470,BK844:BK2470,0) -> 23 | BP844: =RANK(BL844:BL2470,BL844:BL2470,0) -> 1 | BQ844: =Table2[[#This Row],[Column1]]+Table2[[#This Row],[Column2]] -> 24 | BW844: Migo | BX844: 37 | BY844: 0
A845: Magic Eden | B845: 22 | G845: Lusha | H845: 245 | N845: Lusha | O845: 1 | AD845: =AA841 -> Consumer | AF845: =GETPIVOTDATA("funds_raised_millions",$AF$842) -> 1601450 | AI845: #Paid | AJ845: 1 | AL845: &Open | AM845: 1 | AW845: &Open | AX845: 9 | BC845: &Open | BD845: 35 | BJ845: Microsoft | BK845: 1 | BL845: 10000 | BN845: 1stdibs | BO845: =RANK(BK845:BK2471,BK845:BK2471,0) -> 22 | BP845: =RANK(BL845:BL2471,BL845:BL2471,0) -> 1 | BQ845: =Table2[[#This Row],[Column1]]+Table2[[#This Row],[Column2]] -> 23 | BW845: Milkrun | BX845: 86 | BY845: 0
A846: Magic Leap | B846: 1000 | G846: Luxury Presence | H846: 31 | K846: Sum of total_laid_off | N846: Luxury Presence | O846: 1 | AI846: &Open | AJ846: 1 | AL846: 100 Thieves | AM846: 1 | AW846: 100 Thieves | AX846: 12 | BC846: 100 Thieves | BD846: 120 | BJ846: Ericsson | BK846: 663 | BL846: 8500 | BN846: 2TM | BO846: =RANK(BK846:BK2472,BK846:BK2472,0) -> 17 | BP846: =RANK(BL846:BL2472,BL846:BL2472,0) -> 1 | BQ846: =Table2[[#This Row],[Column1]]+Table2[[#This Row],[Column2]] -> 18 | BW846: MindBody | BX846: 228 | BY846: 1100
A847: Magicbricks | B847: 250 | G847: Lyft | H847: 14700 | K847: 383159 | N847: Lyft | O847: 3 | AI847: 100 Thieves | AJ847: 1 | AL847: 10X Genomics | AM847: 1 | AW847: 10X Genomics | AX847: 100 | BC847: 10X Genomics | BD847: 242 | BJ847: Uber | BK847: 123500 | BL847: 7585 | BN847: 2U | BO847: =RANK(BK847:BK2473,BK847:BK2473,0) -> 1 | BP847: =RANK(BL847:BL2473,BL847:BL2473,0) -> 1 | BQ847: =Table2[[#This Row],[Column1]]+Table2[[#This Row],[Column2]] -> 2 | BW847: Mindstrong | BX847: 160 | BY847: 127
A848: Magnite | B848: 0 | G848: Lyric | H848: 179 | N848: Lyric | O848: 1 | U848: =BZ14 -> Amazon | V848: =GETPIVOTDATA("total_laid_off",$BZ$13,"company","Blackbaud") -> #REF! | Z848: industry | AA848: Max of percentage_laid_off | AC848: =COUNTIF(AA849:AA1671,1) -> 61 | AE848: =COUNTA(AA849:AA1671) -> 823 | AI848: 10X Genomics | AJ848: 1 | AL848: 1stdibs | AM848: 1 | AW848: 1stdibs | AX848: 70 | BC848: 1stdibs | BD848: 253 | BJ848: Dell | BK848: 0 | BL848: 6650 | BN848: 54gene | BO848: =RANK(BK848:BK2474,BK848:BK2474,0) -> 20 | BP848: =RANK(BL848:BL2474,BL848:BL2474,0) -> 1 | BQ848: =Table2[[#This Row],[Column1]]+Table2[[#This Row],[Column2]] -> 21 | BW848: Minted | BX848: 297 | BY848: 147
A849: Mainstreet | B849: 45 | G849: Lyst | H849: 144 | N849: Lyst | O849: 1 | Z849: 99 | AA849: 0.02 | AC849: =AC848/AE848 -> 0.074119077 | AI849: 1stdibs | AJ849: 1 | AL849: 2TM | AM849: 2 | AW849: 2TM | AX849: 190 | BC849: 2TM | BD849: 500 | BJ849: Booking.com | BK849: 0 | BL849: 4601 | BN849: 5B Solar | BO849: =RANK(BK849:BK2475,BK849:BK2475,0) -> 20 | BP849: =RANK(BL849:BL2475,BL849:BL2475,0) -> 1 | BQ849: =Table2[[#This Row],[Column1]]+Table2[[#This Row],[Column2]] -> 21 | BW849: Minute Media | BX849: 160 | BY849: 50
A850: MakeMyTrip | B850: 700 | G850: M1 | H850: 323 | N850: M1 | O850: 1 | Z850: #Paid | AA850: 0.17 | AC850: =AC849 -> 0.074119077 | AF850: =AF845/AI840 -> 1945.8688 | AI850: 2TM | AJ850: 2 | AL850: 2U | AM850: 1 | AW850: 54gene | AX850: 95 | BC850: 2U | BD850: 426 | BJ850: Cisco | BK850: 2 | BL850: 4100 | BN850: 6sense | BO850: =RANK(BK850:BK2476,BK850:BK2476,0) -> 19 | BP850: =RANK(BL850:BL2476,BL850:BL2476,0) -> 1 | BQ850: =Table2[[#This Row],[Column1]]+Table2[[#This Row],[Column2]] -> 20 | BW850: Miro | BX850: 476 | BY850: 119
A851: MakerBot | B851: 12 | G851: Made.com | H851: 136 | N851: Made.com | O851: 1 | Z851: &Open | AA851: 0.09 | AI851: 2U | AJ851: 1 | AL851: 54gene | AM851: 1 | AW851: 6sense | AX851: 150 | BC851: 54gene | BD851: 44 | BJ851: Peloton | BK851: 5700 | BL851: 4084 | BN851: 80 Acres Farms | BO851: =RANK(BK851:BK2477,BK851:BK2477,0) -> 7 | BP851: =RANK(BL851:BL2477,BL851:BL2477,0) -> 1 | BQ851: =Table2[[#This Row],[Column1]]+Table2[[#This Row],[Column2]] -> 8 | BW851: Misfits Market | BX851: 526 | BY851: 649
...

Sheet Sheet1
E1: com | F1: funding | G1: layoffs
A2: Meta | B2: 37000 | E2: uber | F2: 123500 | G2: 7585
A3: uber | B3: =GETPIVOTDATA("Sum of funds_raised_millions",an!$BJ$839,"company","Uber")+GETPIVOTDATA("Sum of total_laid_off",an!$BJ$839,"company","Uber") -> 131085 | E3: twitter | F3: 38700 | G3: 3940
A4: peloton | B4: =GETPIVOTDATA("Sum of funds_raised_millions",an!$BJ$839,"company","Peloton")+GETPIVOTDATA("Sum of total_laid_off",an!$BJ$839,"company","Peloton") -> 9784 | E4: bytendance | F4: 35600 | G4: 3750
A5: byju's | B5: =GETPIVOTDATA("Sum of funds_raised_millions",an!$BJ$839,"company","Byju's")+GETPIVOTDATA("Sum of total_laid_off",an!$BJ$839,"company","Byju's") -> 15000 | E5: meta | F5: 26000 | G5: 11000
A6: twitter | B6: =GETPIVOTDATA("Sum of funds_raised_millions",an!$BJ$839,"company","Twitter")+GETPIVOTDATA("Sum of total_laid_off",an!$BJ$839,"company","Twitter") -> 42640 | E6: ola | F6: 18800 | G6: 2800
A7: bytendance | B7: =GETPIVOTDATA("Sum of funds_raised_millions",an!$BJ$839,"company","Bytedance")+GETPIVOTDATA("Sum of total_laid_off",an!$BJ$839,"company","Bytedance") -> 39350
A8: swiggy | B8: =GETPIVOTDATA("Sum of funds_raised_millions",an!$BJ$839,"company","Swiggy")+GETPIVOTDATA("Sum of total_laid_off",an!$BJ$839,"company","Swiggy") -> 14880
A9: ola | B9: =GETPIVOTDATA("Sum of funds_raised_millions",an!$BJ$839,"company","Ola")+GETPIVOTDATA("Sum of total_laid_off",an!$BJ$839,"company","Ola") -> 21600
A10: gopuff | B10: =GETPIVOTDATA("Sum of funds_raised_millions",an!$BJ$839,"company","Gopuff")+GETPIVOTDATA("Sum of total_laid_off",an!$BJ$839,"company","Gopuff") -> 15900

Sheet overview

Sheet analysis

Sheet insights

Sheet Sheet2
M1: =IFERROR(M4,0) -> Consumer | N1: =N4 -> 45182 | P1: =COUNTIF(Table[percentage_laid_off],1) -> 116 | Q1: =SUMPRODUCT((A2:A1996<>"")/COUNTIF(A2:A1996,A2:A1996&"")) -> 1629 | AO1: =IFERROR(GETPIVOTDATA("total_laid_off",$AN$2),0) -> 256059
Q2: =P1/Q1 -> 0.071209331 | AF2: Row Labels | AG2: Sum of total_laid_off | AN2: Row Labels | AO2: Sum of total_laid_off
A3: Row Labels | B3: Sum of total_laid_off | F3: Row Labels | G3: Max of funds_raised_millions | M3: Row Labels | N3: Sum of total_laid_off | U3: Row Labels | V3: Count of company | W3: Count of helped | AF3: Apr | AG3: 31099 | AN3: United States | AO3: 256059
A4: 99 | B4: 75 | D4: =AVERAGEIF(B4:B1630,">"&0) -> 288.74077 | F4: 99 | G4: 244 | I4: =AVERAGEIF(G4:G1630,">"&0) -> 546.31861 | M4: Consumer | N4: 45182 | U4: Funded & Laid Off | V4: 1988 | W4: 0.99699097 | X4: =GETPIVOTDATA("Count of helped",$U$3,"helped","Funded & Laid Off") -> 0.99699097 | AF4: Aug | AG4: 16891 | AN4: Grand Total | AO4: 256059
A5: #Paid | B5: 19 | F5: #Paid | G5: 21 | U5: No Funding Laid Off | V5: 6 | W5: 0.0030090271 | AF5: Dec | AG5: 12381
A6: &Open | B6: 9 | F6: &Open | G6: 35 | U6: Grand Total | V6: 1994 | W6: 1 | AF6: Feb | AG6: 41046
A7: 100 Thieves | B7: 12 | F7: 100 Thieves | G7: 120 | N7: =IFERROR(GETPIVOTDATA("total_laid_off",$M$3),0) -> 0 | AF7: Jan | AG7: 92037
A8: 10X Genomics | B8: 100 | F8: 10X Genomics | G8: 242 | AF8: Jul | AG8: 23415
A9: 1stdibs | B9: 70 | F9: 1stdibs | G9: 253 | AF9: Jun | AG9: 27455
A10: 2TM | B10: 190 | F10: 2TM | G10: 250 | AF10: Mar | AG10: 19859
A11: 2U | B11: 0 | F11: 2U | G11: 426 | AF11: May | AG11: 38689
A12: 54gene | B12: 95 | F12: 54gene | G12: 44 | AF12: Nov | AG12: 55758
A13: 5B Solar | B13: 0 | F13: 5B Solar | G13: 12 | AF13: Oct | AG13: 17878
A14: 6sense | B14: 150 | F14: 6sense | G14: 426 | AF14: Sep | AG14: 6651
A15: 80 Acres Farms | B15: 0 | F15: 80 Acres Farms | G15: 275 | AF15: Grand Total | AG15: 383159
A16: 8x8 | B16: 355 | F16: 8x8 | G16: 253
A17: 98point6 | B17: 0 | F17: 98point6 | G17: 247
A18: Abra | B18: 12 | F18: Abra | G18: 106
A19: Absci | B19: 40 | F19: Absci | G19: 237
A20: Acast | B20: 70 | F20: Acast | G20: 126
A21: Acko | B21: 45 | F21: Acko | G21: 143
A22: Acorns | B22: 50 | F22: Acorns | G22: 207
A23: Actifio | B23: 54 | F23: Actifio | G23: 352
A24: ActiveCampaign | B24: 0 | F24: ActiveCampaign | G24: 360
A25: Ada | B25: 78 | F25: Ada | G25: 190
A26: Ada Health | B26: 50 | F26: Ada Health | G26: 189
A27: Ada Support | B27: 36 | F27: Ada Support | G27: 60
... A1631: Grand Total | B1631: 383159 | F1631: Grand Total | G1631: 121900

Sheet dataset
A1: company | B1: location | C1: industry | D1: total_laid_off | E1: percentage_laid_off | F1: date | G1: month | H1: year | I1: stage | J1: country | K1: funds_raised_millions
A2: Included Health | B2: SF Bay Area | C2: Healthcare | D2: NULL | E2: 0.06 | F2: 44767 | G2: =TEXT(Table[[#This Row],[date]],"mmm") -> Jul | H2: =TEXT(Table[[#This Row],[date]],"yyyy") -> 2022 | I2: Series E | J2: United States | K2: 272
A3: &Open | B3: Dublin | C3: Marketing | D3: 9 | E3: 0.09 | F3: 44882 | G3: =TEXT(Table[[#This Row],[date]],"mmm") -> Nov | H3: =TEXT(Table[[#This Row],[date]],"yyyy") -> 2022 | I3: Series A | J3: Ireland | K3: 35
A4: #Paid | B4: Toronto | C4: Marketing | D4: 19 | E4: 0.17 | F4: 44953 | G4: =TEXT(Table[[#This Row],[date]],"mmm") -> Jan | H4: =TEXT(Table[[#This Row],[date]],"yyyy") -> 2023 | I4: Series B | J4: Canada | K4: 21
A5: 100 Thieves | B5: Los Angeles | C5: Consumer | D5: 12 | E5: NULL | F5: 44755 | G5: =TEXT(Table[[#This Row],[date]],"mmm") -> Jul | H5: =TEXT(Table[[#This Row],[date]],"yyyy") -> 2022 | I5: Series C | J5: United States | K5: 120
A6: 10X Genomics | B6: SF Bay Area | C6: Healthcare | D6: 100 | E6: 0.08 | F6: 44777 | G6: =TEXT(Table[[#This Row],[date]],"mmm") -> Aug | H6: =TEXT(Table[[#This Row],[date]],"yyyy") -> 2022 | I6: Post-IPO | J6: United States | K6: 242
A7: 1stdibs | B7: New York City | C7: Retail | D7: 70 | E7: 0.17 | F7: 43923 | G7: =TEXT(Table[[#This Row],[date]],"mmm") -> Apr | H7: =TEXT(Table[[#This Row],[date]],"yyyy") -> 2020 | I7: Series D | J7: United States | K7: 253
A8: 2TM | B8: Sao Paulo | C8: crypto | D8: 90 | E8: 0.12 | F8: 44713 | G8: =TEXT(Table[[#This Row],[date]],"mmm") -> Jun | H8: =TEXT(Table[[#This Row],[date]],"yyyy") -> 2022 | I8: Unknown | J8: Brazil | K8: 250
A9: 2TM | B9: Sao Paulo | C9: crypto | D9: 100 | E9: 0.15 | F9: 44805 | G9: =TEXT(Table[[#This Row],[date]],"mmm") -> Sep | H9: =TEXT(Table[[#This Row],[date]],"yyyy") -> 2022 | I9: Unknown | J9: Brazil | K9: 250
A10: 2U | B10: Washington D.C. | C10: Education | D10: NULL | E10: 0.2 | F10: 44770 | G10: =TEXT(Table[[#This Row],[date]],"mmm") -> Jul | H10: =TEXT(Table[[#This Row],[date]],"yyyy") -> 2022 | I10: Post-IPO | J10: United States | K10: 426
A11: 54gene | B11: Washington D.C. | C11: Healthcare | D11: 95 | E11: 0.3 | F11: 44802 | G11: =TEXT(Table[[#This Row],[date]],"mmm") -> Aug | H11: =TEXT(Table[[#This Row],[date]],"yyyy") -> 2022 | I11: Series B | J11: United States | K11: 44
A12: 5B Solar | B12: Sydney | C12: Energy | D12: NULL | E12: 0.25 | F12: 44715 | G12: =TEXT(Table[[#This Row],[date]],"mmm") -> Jun | H12: =TEXT(Table[[#This Row],[date]],"yyyy") -> 2022 | I12: Series A | J12: Australia | K12: 12
A13: 6sense | B13: SF Bay Area | C13: Sales | D13: 150 | E13: 0.1 | F13: 44846 | G13: =TEXT(Table[[#This Row],[date]],"mmm") -> Oct | H13: =TEXT(Table[[#This Row],[date]],"yyyy") -> 2022 | I13: Series E | J13: United States | K13: 426
A14: 80 Acres Farms | B14: Cincinnati | C14: Food | D14: NULL | E14: 0.1 | F14: 44944 | G14: =TEXT(Table[[#This Row],[date]],"mmm") -> Jan | H14: =TEXT(Table[[#This Row],[date]],"yyyy") -> 2023 | I14: Unknown | J14: United States | K14: 275
A15: 8x8 | B15: SF Bay Area | C15: Support | D15: 155 | E15: 0.07 | F15: 44944 | G15: =TEXT(Table[[#This Row],[date]],"mmm") -> Jan | H15: =TEXT(Table[[#This Row],[date]],"yyyy") -> 2023 | I15: Post-IPO | J15: United States | K15: 253
A16: 8x8 | B16: SF Bay Area | C16: Support | D16: 200 | E16: 0.09 | F16: 44838 | G16: =TEXT(Table[[#This Row],[date]],"mmm") -> Oct | H16: =TEXT(Table[[#This Row],[date]],"yyyy") -> 2022 | I16: Post-IPO | J16: United States | K16: 253
A17: 98point6 | B17: Seattle | C17: Healthcare | D17: NULL | E17: 0.1 | F17: 44763 | G17: =TEXT(Table[[#This Row],[date]],"mmm") -> Jul | H17: =TEXT(Table[[#This Row],[date]],"yyyy") -> 2022 | I17: Series E | J17: United States | K17: 247
A18: 99 | B18: Sao Paulo | C18: Transportation | D18: 75 | E18: 0.02 | F18: 44824 | G18: =TEXT(Table[[#This Row],[date]],"mmm") -> Sep | H18: =TEXT(Table[[#This Row],[date]],"yyyy") -> 2022 | I18: Acquired | J18: Brazil | K18: 244
A19: Abra | B19: SF Bay Area | C19: crypto | D19: 12 | E19: 0.05 | F19: 44742 | G19: =TEXT(Table[[#This Row],[date]],"mmm") -> Jun | H19: =TEXT(Table[[#This Row],[date]],"yyyy") -> 2022 | I19: Series C | J19: United States | K19: 106
A20: Absci | B20: Vancouver | C20: Healthcare | D20: 40 | E20: NULL | F20: 44782 | G20: =TEXT(Table[[#This Row],[date]],"mmm") -> Aug | H20: =TEXT(Table[[#This Row],[date]],"yyyy") -> 2022 | I20: Post-IPO | J20: United States | K20: 237
A21: Acast | B21: Stockholm | C21: Media | D21: 70 | E21: 0.15 | F21: 44819 | G21: =TEXT(Table[[#This Row],[date]],"mmm") -> Sep | H21: =TEXT(Table[[#This Row],[date]],"yyyy") -> 2022 | I21: Post-IPO | J21: Sweden | K21: 126
A22: Acko | B22: Mumbai | C22: Finance | D22: 45 | E22: 0.09 | F22: 43922 | G22: =TEXT(Table[[#This Row],[date]],"mmm") -> Apr | H22: =TEXT(Table[[#This Row],[date]],"yyyy") -> 2020 | I22: Unknown | J22: India | K22: 143
A23: Acorns | B23: Portland | C23: Finance | D23: 50 | E23: NULL | F23: 43977 | G23: =TEXT(Table[[#This Row],[date]],"mmm") -> May | H23: =TEXT(Table[[#This Row],[date]],"yyyy") -> 2020 | I23: Unknown | J23: United States | K23: 207
A24: Actifio | B24: Boston | C24: Data | D24: 54 | E24: NULL | F24: 44181 | G24: =TEXT(Table[[#This Row],[date]],"mmm") -> Dec | H24: =TEXT(Table[[#This Row],[date]],"yyyy") -> 2020 | I24: Acquired | J24: United States | K24: 352
A25: ActiveCampaign | B25: Chicago | C25: Marketing | D25: NULL | E25: 0.15 | F25: 44837 | G25: =TEXT(Table[[#This Row],[date]],"mmm") -> Oct | H25: =TEXT(Table[[#This Row],[date]],"yyyy") -> 2022 | I25: Series C | J25: United States | K25: 360
A26: Ada | B26: Toronto | C26: Support | D26: 78 | E26: 0.16 | F26: 44824 | G26: =TEXT(Table[[#This Row],[date]],"mmm") -> Sep | H26: =TEXT(Table[[#This Row],[date]],"yyyy") -> 2022 | I26: Series C | J26: Canada | K26: 190
A27: Ada Health | B27: Berlin | C27: Healthcare | D27: 50 | E27: NULL | F27: 44851 | G27: =TEXT(Table[[#This Row],[date]],"mmm") -> Oct | H27: =TEXT(Table[[#This Row],[date]],"yyyy") -> 2022 | I27: Series B | J27: Germany | K27: 189
A28: Ada Support | B28: Toronto | C28: Support | D28: 36 | E28: 0.23 | F28: 43945 | G28: =TEXT(Table[[#This Row],[date]],"mmm") -> Apr | H28: =TEXT(Table[[#This Row],[date]],"yyyy") -> 2020 | I28: Series B | J28: Canada | K28: 60
A29: Adaptive Biotechnologies | B29: Seattle | C29: Healthcare | D29: 100 | E29: 0.12 | F29: 44628 | G29: =TEXT(Table[[#This Row],[date]],"mmm") -> Mar | H29: =TEXT(Table[[#This Row],[date]],"yyyy") -> 2022 | I29: Post-IPO | J29: United States | K29: 406
A30: Addepar | B30: SF Bay Area | C30: Finance | D30: 20 | E30: 0.03 | F30: 44944 | G30: =TEXT(Table[[#This Row],[date]],"mmm") -> Jan | H30: =TEXT(Table[[#This Row],[date]],"yyyy") -> 2023 | I30: Series F | J30: United States | K30: 491
A31: Adobe | B31: SF Bay Area | C31: Marketing | D31: 100 | E31: NULL | F31: 44901 | G31: =TEXT(Table[[#This Row],[date]],"mmm") -> Dec | H31: =TEXT(Table[[#This Row],[date]],"yyyy") -> 2022 | I31: Post-IPO | J31: United States | K31: 2
A32: AdRoll | B32: Salt Lake City | C32: Marketing | D32: 210 | E32: 0.3 | F32: 43921 | G32: =TEXT(Table[[#This Row],[date]],"mmm") -> Mar | H32: =TEXT(Table[[#This Row],[date]],"yyyy") -> 2020 | I32: Series C | J32: United States | K32: 89
A33: Advata | B33: Seattle | C33: Healthcare | D33: 32 | E33: 0.21 | F33: 44862 | G33: =TEXT(Table[[#This Row],[date]],"mmm") -> Oct | H33: =TEXT(Table[[#This Row],[date]],"yyyy") -> 2022 | I33: NULL | J33: United States | K33: NULL
A34: Adwerx | B34: Durham | C34: Marketing | D34: 40 | E34: NULL | F34: 44749 | G34: =TEXT(Table[[#This Row],[date]],"mmm") -> Jul | H34: =TEXT(Table[[#This Row],[date]],"yyyy") -> 2022 | I34: Unknown | J34: United States | K34: 20
A35: Affirm | B35: SF Bay Area | C35: Finance | D35: NULL | E35: 0.01 | F35: 44868 | G35: =TEXT(Table[[#This Row],[date]],"mmm") -> Nov | H35: =TEXT(Table[[#This Row],[date]],"yyyy") -> 2022 | I35: Post-IPO | J35: United States | K35: 1500
A36: Affirm | B36: SF Bay Area | C36: Finance | D36: 500 | E36: 0.19 | F36: 44965 | G36: =TEXT(Table[[#This Row],[date]],"mmm") -> Feb | H36: =TEXT(Table[[#This Row],[date]],"yyyy") -> 2023 | I36: Post-IPO | J36: United States | K36: 1500
A37: Afterverse | B37: Brasilia | C37: Consumer | D37: 60 | E37: 0.2 | F37: 44715 | G37: =TEXT(Table[[#This Row],[date]],"mmm") -> Jun | H37: =TEXT(Table[[#This Row],[date]],"yyyy") -> 2022 | I37: Unknown | J37: Brazil | K37: NULL
A38: Agoda | B38: Singapore | C38: Travel | D38: 1500 | E38: 0.25 | F38: 43969 | G38: =TEXT(Table[[#This Row],[date]],"mmm") -> May | H38: =TEXT(Table[[#This Row],[date]],"yyyy") -> 2020 | I38: Acquired | J38: Singapore | K38: NULL
A39: Ahead | B39: SF Bay Area | C39: Healthcare | D39: 44 | E39: 1 | F39: 44665 | G39: =TEXT(Table[[#This Row],[date]],"mmm") -> Apr | H39: =TEXT(Table[[#This Row],[date]],"yyyy") -> 2022 | I39: Unknown | J39: United States | K39: 9
A40: Air | B40: New York City | C40: Marketing | D40: NULL | E40: 0.16 | F40: 44090 | G40: =TEXT(Table[[#This Row],[date]],"mmm") -> Sep | H40: =TEXT(Table[[#This Row],[date]],"yyyy") -> 2020 | I40: Series A | J40: United States | K40: 18
A41: Airbnb | B41: SF Bay Area | C41: Travel | D41: 30 | E41: NULL | F41: 44988 | G41: =TEXT(Table[[#This Row],[date]],"mmm") -> Mar | H41: =TEXT(Table[[#This Row],[date]],"yyyy") -> 2023 | I41: Post-IPO | J41: United States | K41: 6400
A42: Airbnb | B42: SF Bay Area | C42: Travel | D42: 1900 | E42: 0.25 | F42: 43956 | G42: =TEXT(Table[[#This Row],[date]],"mmm") -> May | H42: =TEXT(Table[[#This Row],[date]],"yyyy") -> 2020 | I42: Private Equity | J42: United States | K42: 5400
A43: Airlift | B43: Lahore | C43: Logistics | D43: NULL | E43: 0.31 | F43: 44706 | G43: =TEXT(Table[[#This Row],[date]],"mmm") -> May | H43: =TEXT(Table[[#This Row],[date]],"yyyy") -> 2022 | I43: Series B | J43: Pakistan | K43: 109
A44: Airlift | B44: Lahore | C44: Logistics | D44: NULL | E44: 1 | F44: 44754 | G44: =TEXT(Table[[#This Row],[date]],"mmm") -> Jul | H44: =TEXT(Table[[#This Row],[date]],"yyyy") -> 2022 | I44: Series B | J44: Pakistan | K44: 109
A45: Airtable | B45: SF Bay Area | C45: Product | D45: 254 | E45: 0.2 | F45: 44903 | G45: =TEXT(Table[[#This Row],[date]],"mmm") -> Dec | H45: =TEXT(Table[[#This Row],[date]],"yyyy") -> 2022 | I45: Series F | J45: United States | K45: 1400
A46: Airtame | B46: Copenhagen | C46: Consumer | D46: 15 | E46: NULL | F46: 44727 | G46: =TEXT(Table[[#This Row],[date]],"mmm") -> Jun | H46: =TEXT(Table[[#This Row],[date]],"yyyy") -> 2022 | I46: Unknown | J46: Denmark | K46: 7
A47: Airtime | B47: New York City | C47: Consumer | D47: 30 | E47: 0.2 | F47: 44704 | G47: =TEXT(Table[[#This Row],[date]],"mmm") -> May | H47: =TEXT(Table[[#This Row],[date]],"yyyy") -> 2022 | I47: Series B | J47: United States | K47: 33
A48: Airy Rooms | B48: Jakarta | C48: Travel | D48: NULL | E48: 0.7 | F48: 43943 | G48: =TEXT(Table[[#This Row],[date]],"mmm") -> Apr | H48: =TEXT(Table[[#This Row],[date]],"yyyy") -> 2020 | I48: Unknown | J48: Indonesia | K48: NULL
A49: Airy Rooms | B49: Jakarta | C49: Travel | D49: NULL | E49: 1 | F49: 43958 | G49: =TEXT(Table[[#This Row],[date]],"mmm") -> May | H49: =TEXT(Table[[#This Row],[date]],"yyyy") -> 2020 | I49: Unknown | J49: Indonesia | K49: NULL
A50: Aiven | B50: Helsinki | C50: Infrastructure | D50: NULL | E50: 0.2 | F50: 44944 | G50: =TEXT(Table[[#This Row],[date]],"mmm") -> Jan | H50: =TEXT(Table[[#This Row],[date]],"yyyy") -> 2023 | I50: Series D | J50: Finland | K50: 420
A51: Ajaib | B51: Jakarta | C51: Finance | D51: 67 | E51: 0.08 | F51: 44893 | G51: =TEXT(Table[[#This Row],[date]],"mmm") -> Nov | H51: =TEXT(Table[[#This Row],[date]],"yyyy") -> 2022 | I51: Unknown | J51: Indonesia | K51: 245
A52: Akili Labs | B52: Baltimore | C52: Healthcare | D52: 46 | E52: 0.3 | F52: 44938 | G52: =TEXT(Table[[#This Row],[date]],"mmm") -> Jan | H52: =TEXT(Table[[#This Row],[date]],"yyyy") -> 2023 | I52: Seed | J52: United States | K52: NULL
A53: Akulaku | B53: Jakarta | C53: Finance | D53: 100 | E53: NULL | F53: 43936 | G53: =TEXT(Table[[#This Row],[date]],"mmm") -> Apr | H53: =TEXT(Table[[#This Row],[date]],"yyyy") -> 2020 | I53: Series D | J53: Indonesia | K53: 160
A54: AlayaCare | B54: Montreal | C54: Healthcare | D54: 80 | E54: 0.14 | F54: 44789 | G54: =TEXT(Table[[#This Row],[date]],"mmm") -> Aug | H54: =TEXT(Table[[#This Row],[date]],"yyyy") -> 2022 | I54: Series D | J54: Canada | K54: 293
A55: Albert | B55: Los Angeles | C55: Finance | D55: 20 | E55: 0.08 | F55: 44722 | G55: =TEXT(Table[[#This Row],[date]],"mmm") -> Jun | H55: =TEXT(Table[[#This Row],[date]],"yyyy") -> 2022 | I55: Series C | J55: United States | K55: 175
A56: Alerzo | B56: Ibadan | C56: Retail | D56: 400 | E56: NULL | F56: 44991 | G56: =TEXT(Table[[#This Row],[date]],"mmm") -> Mar | H56: =TEXT(Table[[#This Row],[date]],"yyyy") -> 2023 | I56: Series B | J56: Nigeria | K56: 16
A57: Alice | B57: Sao Paulo | C57: Healthcare | D57: 63 | E57: NULL | F57: 44753 | G57: =TEXT(Table[[#This Row],[date]],"mmm") -> Jul | H57: =TEXT(Table[[#This Row],[date]],"yyyy") -> 2022 | I57: Series C | J57: Brazil | K57: 174
A58: Alice | B58: Sao Paulo | C58: Healthcare | D58: 113 | E58: 0.16 | F58: 44904 | G58: =TEXT(Table[[#This Row],[date]],"mmm") -> Dec | H58: =TEXT(Table[[#This Row],[date]],"yyyy") -> 2022 | I58: Series C | J58: Brazil | K58: 174
A59: AliExpress Russia | B59: Moscow | C59: Retail | D59: 400 | E59: 0.4 | F59: 44695 | G59: =TEXT(Table[[#This Row],[date]],"mmm") -> May | H59: =TEXT(Table[[#This Row],[date]],"yyyy") -> 2022 | I59: Acquired | J59: Russia | K59: 60
A60: Allbirds | B60: SF Bay Area | C60: Retail | D60: 23 | E60: NULL | F60: 44770 | G60: =TEXT(Table[[#This Row],[date]],"mmm") -> Jul | H60: =TEXT(Table[[#This Row],[date]],"yyyy") -> 2022 | I60: Post-IPO | J60: United States | K60: 202
A61: Alto Pharmacy | B61: SF Bay Area | C61: Healthcare | D61: 47 | E61: 0.06 | F61: 44103 | G61: =TEXT(Table[[#This Row],[date]],"mmm") -> Sep | H61: =TEXT(Table[[#This Row],[date]],"yyyy") -> 2020 | I61: Series D | J61: United States | K61: 356
A62: Amazon | B62: Seattle | C62: Retail | D62: 150 | E62: NULL | F62: 44862 | G62: =TEXT(Table[[#This Row],[date]],"mmm") -> Oct | H62: =TEXT(Table[[#This Row],[date]],"yyyy") -> 2022 | I62: Post-IPO | J62: United States | K62: 108
A63: Amazon | B63: Seattle | C63: Retail | D63: 8000 | E63: 0.02 | F63: 44930 | G63: =TEXT(Table[[#This Row],[date]],"mmm") -> Jan | H63: =TEXT(Table[[#This Row],[date]],"yyyy") -> 2023 | I63: Post-IPO | J63: United States | K63: 108
A64: Amazon | B64: Seattle | C64: Retail | D64: 10000 | E64: 0.03 | F64: 44881 | G64: =TEXT(Table[[#This Row],[date]],"mmm") -> Nov | H64: =TEXT(Table[[#This Row],[date]],"yyyy") -> 2022 | I64: Post-IPO | J64: United States | K64: 108
A65: Amber Group | B65: Hong Kong | C65: crypto | D65: NULL | E65: 0.1 | F65: 44813 | G65: =TEXT(Table[[#This Row],[date]],"mmm") -> Sep | H65: =TEXT(Table[[#This Row],[date]],"yyyy") -> 2022 | I65: Series B | J65: Hong Kong | K65: 328
A66: Ambev Tech | B66: Blumenau | C66: Food | D66: 50 | E66: NULL | F66: 44987 | G66: =TEXT(Table[[#This Row],[date]],"mmm") -> Mar | H66: =TEXT(Table[[#This Row],[date]],"yyyy") -> 2023 | I66: Acquired | J66: Brazil | K66: NULL
A67: Amdocs | B67: St. Louis | C67: Support | D67: 700 | E67: 0.03 | F67: 44928 | G67: =TEXT(Table[[#This Row],[date]],"mmm") -> Jan | H67: =TEXT(Table[[#This Row],[date]],"yyyy") -> 2023 | I67: Post-IPO | J67: United States | K67: NULL
A68: American Robotics | B68: Boston | C68: Other | D68: 50 | E68: 0.65 | F68: 44943 | G68: =TEXT(Table[[#This Row],[date]],"mmm") -> Jan | H68: =TEXT(Table[[#This Row],[date]],"yyyy") -> 2023 | I68: Acquired | J68: United States | K68: 92
A69: Amount | B69: Chicago | C69: Finance | D69: NULL | E69: 0.18 | F69: 44739 | G69: =TEXT(Table[[#This Row],[date]],"mmm") -> Jun | H69: =TEXT(Table[[#This Row],[date]],"yyyy") -> 2022 | I69: Unknown | J69: United States | K69: 283
A70: Amount | B70: Chicago | C70: Finance | D70: 130 | E70: 0.25 | F70: 44984 | G70: =TEXT(Table[[#This Row],[date]],"mmm") -> Feb | H70: =TEXT(Table[[#This Row],[date]],"yyyy") -> 2023 | I70: Unknown | J70: United States | K70: 283
A71: Amperity | B71: Seattle | C71: Marketing | D71: 13 | E71: 0.03 | F71: 44793 | G71: =TEXT(Table[[#This Row],[date]],"mmm") -> Aug | H71: =TEXT(Table[[#This Row],[date]],"yyyy") -> 2022 | I71: Series D | J71: United States | K71: 187
A72: Amplero | B72: Seattle | C72: Marketing | D72: 17 | E72: 1 | F72: 43919 | G72: =TEXT(Table[[#This Row],[date]],"mmm") -> Mar | H72: =TEXT(Table[[#This Row],[date]],"yyyy") -> 2020 | I72: Series B | J72: United States | K72: 25
A73: Anagram | B73: Los Angeles | C73: Healthcare | D73: 17 | E73: NULL | F73: 43924 | G73: =TEXT(Table[[#This Row],[date]],"mmm") -> Apr | H73: =TEXT(Table[[#This Row],[date]],"yyyy") -> 2020 | I73: Series A | J73: United States | K73: 14
A74: Andela | B74: New York City | C74: Recruiting | D74: 135 | E74: 0.1 | F74: 43956 | G74: =TEXT(Table[[#This Row],[date]],"mmm") -> May | H74: =TEXT(Table[[#This Row],[date]],"yyyy") -> 2020 | I74: Series D | J74: United States | K74: 181
A75: AngelList | B75: SF Bay Area | C75: Recruiting | D75: 20 | E75: NULL | F75: 43921 | G75: =TEXT(Table[[#This Row],[date]],"mmm") -> Mar | H75: =TEXT(Table[[#This Row],[date]],"yyyy") -> 2020 | I75: Series B | J75: United States | K75: 26
A76: Anodot | B76: Tel Aviv | C76: Data | D76: 35 | E76: 0.27 | F76: 44748 | G76: =TEXT(Table[[#This Row],[date]],"mmm") -> Jul | H76: =TEXT(Table[[#This Row],[date]],"yyyy") -> 2022 | I76: Series C | J76: United States | K76: 64
A77: Antidote Health | B77: Tel Aviv | C77: Healthcare | D77: 23 | E77: 0.38 | F77: 44857 | G77: =TEXT(Table[[#This Row],[date]],"mmm") -> Oct | H77: =TEXT(Table[[#This Row],[date]],"yyyy") -> 2022 | I77: Unknown | J77: Israel | K77: 36
A78: Anywell | B78: Tel Aviv | C78: Real Estate | D78: 11 | E78: NULL | F78: 44787 | G78: =TEXT(Table[[#This Row],[date]],"mmm") -> Aug | H78: =TEXT(Table[[#This Row],[date]],"yyyy") -> 2022 | I78: Series A | J78: Israel | K78: 15
A79: Apartment List | B79: SF Bay Area | C79: Real Estate | D79: 29 | E79: 0.1 | F79: 44804 | G79: =TEXT(Table[[#This Row],[date]],"mmm") -> Aug | H79: =TEXT(Table[[#This Row],[date]],"yyyy") -> 2022 | I79: Series D | J79: United States | K79: 169
A80: Apollo | B80: SF Bay Area | C80: Product | D80: NULL | E80: 0.15 | F80: 44910 | G80: =TEXT(Table[[#This Row],[date]],"mmm") -> Dec | H80: =TEXT(Table[[#This Row],[date]],"yyyy") -> 2022 | I80: Series D | J80: United States | K80: 183
A81: Apollo Insurance | B81: Vancouver | C81: Finance | D81: NULL | E81: 0.25 | F81: 44880 | G81: =TEXT(Table[[#This Row],[date]],"mmm") -> Nov | H81: =TEXT(Table[[#This Row],[date]],"yyyy") -> 2022 | I81: Series B | J81: Canada | K81: 11
A82: App Annie | B82: SF Bay Area | C82: Data | D82: 80 | E82: 0.18 | F82: 43949 | G82: =TEXT(Table[[#This Row],[date]],"mmm") -> Apr | H82: =TEXT(Table[[#This Row],[date]],"yyyy") -> 2020 | I82: Unknown | J82: United States | K82: 156
A83: Appgate | B83: Miami | C83: Security | D83: 34 | E83: 0.08 | F83: 44958 | G83: =TEXT(Table[[#This Row],[date]],"mmm") -> Feb | H83: =TEXT(Table[[#This Row],[date]],"yyyy") -> 2023 | I83: Post-IPO | J83: United States | K83: NULL
A84: AppGate | B84: Miami | C84: Security | D84: 130 | E84: 0.22 | F84: 44763 | G84: =TEXT(Table[[#This Row],[date]],"mmm") -> Jul | H84: =TEXT(Table[[#This Row],[date]],"yyyy") -> 2022 | I84: Post-IPO | J84: United States | K84: NULL
A85: AppLovin | B85: SF Bay Area | C85: Marketing | D85: 300 | E85: 0.12 | F85: 44739 | G85: =TEXT(Table[[#This Row],[date]],"mmm") -> Jun | H85: =TEXT(Table[[#This Row],[date]],"yyyy") -> 2022 | I85: Post-IPO | J85: United States | K85: 1600
A86: ApplyBoard | B86: Waterloo | C86: Education | D86: 90 | E86: 0.06 | F86: 44893 | G86: =TEXT(Table[[#This Row],[date]],"mmm") -> Nov | H86: =TEXT(Table[[#This Row],[date]],"yyyy") -> 2022 | I86: Series D | J86: Canada | K86: 483
A87: Aqgromalin | B87: Chennai | C87: Food | D87: 80 | E87: 0.3 | F87: 44732 | G87: =TEXT(Table[[#This Row],[date]],"mmm") -> Jun | H87: =TEXT(Table[[#This Row],[date]],"yyyy") -> 2022 | I87: Unknown | J87: India | K87: 12
A88: Aqua Security | B88: Boston | C88: Security | D88: 65 | E88: 0.1 | F88: 44900 | G88: =TEXT(Table[[#This Row],[date]],"mmm") -> Dec | H88: =TEXT(Table[[#This Row],[date]],"yyyy") -> 2022 | I88: Series E | J88: United States | K88: 265
A89: Aqua Security | B89: Tel Aviv | C89: Security | D89: 24 | E89: 0.09 | F89: 43922 | G89: =TEXT(Table[[#This Row],[date]],"mmm") -> Apr | H89: =TEXT(Table[[#This Row],[date]],"yyyy") -> 2020 | I89: Series C | J89: Israel | K89: 100
A90: Arc | B90: SF Bay Area | C90: HR | D90: 13 | E90: NULL | F90: 44762 | G90: =TEXT(Table[[#This Row],[date]],"mmm") -> Jul | H90: =TEXT(Table[[#This Row],[date]],"yyyy") -> 2022 | I90: Seed | J90: United States | K90: 1
A91: Arch Oncology | B91: Brisbane | C91: Healthcare | D91: NULL | E91: 1 | F91: 44939 | G91: =TEXT(Table[[#This Row],[date]],"mmm") -> Jan | H91: =TEXT(Table[[#This Row],[date]],"yyyy") -> 2023 | I91: Series C | J91: United States | K91: 155
A92: Argo AI | B92: Munich | C92: Transportation | D92: 100 | E92: NULL | F92: 44011 | G92: =TEXT(Table[[#This Row],[date]],"mmm") -> Jun | H92: =TEXT(Table[[#This Row],[date]],"yyyy") -> 2020 | I92: Unknown | J92: Germany | K92: 3600
A93: Argo AI | B93: Pittsburgh | C93: Transportation | D93: 150 | E93: 0.05 | F93: 44749 | G93: =TEXT(Table[[#This Row],[date]],"mmm") -> Jul | H93: =TEXT(Table[[#This Row],[date]],"yyyy") -> 2022 | I93: Unknown | J93: United States | K93: 3600
A94: Argo AI | B94: Pittsburgh | C94: Transportation | D94: 173 | E94: NULL | F94: 44860 | G94: =TEXT(Table[[#This Row],[date]],"mmm") -> Oct | H94: =TEXT(Table[[#This Row],[date]],"yyyy") -> 2022 | I94: Unknown | J94: United States | K94: 3600
A95: Argo AI | B95: SF Bay Area | C95: Transportation | D95: 259 | E95: NULL | F95: 44866 | G95: =TEXT(Table[[#This Row],[date]],"mmm") -> Nov | H95: =TEXT(Table[[#This Row],[date]],"yyyy") -> 2022 | I95: Unknown | J95: United States | K95: 3600
A96: Argyle | B96: New York City | C96: Finance | D96: 20 | E96: 0.07 | F96: 44799 | G96: =TEXT(Table[[#This Row],[date]],"mmm") -> Aug | H96: =TEXT(Table[[#This Row],[date]],"yyyy") -> 2022 | I96: Series B | J96: United States | K96: 78
A97: Armis | B97: SF Bay Area | C97: Security | D97: 25 | E97: 0.04 | F97: 44903 | G97: =TEXT(Table[[#This Row],[date]],"mmm") -> Dec | H97: =TEXT(Table[[#This Row],[date]],"yyyy") -> 2022 | I97: Private Equity | J97: United States | K97: 537
A98: Arrival | B98: London | C98: Transportation | D98: NULL | E98: 0.3 | F98: 44755 | G98: =TEXT(Table[[#This Row],[date]],"mmm") -> Jul | H98: =TEXT(Table[[#This Row],[date]],"yyyy") -> 2022 | I98: Post-IPO | J98: United Kingdom | K98: 629
A99: Arrival | B99: London | C99: Transportation | D99: 800 | E99: 0.5 | F99: 44956 | G99: =TEXT(Table[[#This Row],[date]],"mmm") -> Jan | H99: =TEXT(Table[[#This Row],[date]],"yyyy") -> 2023 | I99: Post-IPO | J99: United Kingdom | K99: 629
A100: Arrive Logistics | B100: Austin | C100: Logistics | D100: 75 | E100: 0.07 | F100: 43924 | G100: =TEXT(Table[[#This Row],[date]],"mmm") -> Apr | H100: =TEXT(Table[[#This Row],[date]],"yyyy") -> 2020 | I100: Series B | J100: United States | K100: 35
...

Sheet Dashboard Instructions
